Metadata-Version: 1.0
Name: isdc-geobaseline
Version: 1.0.0
Summary: baseline module
Home-page: UNKNOWN
Author: iMMAP
Author-email: asdc@immap.org
License: iMMAP
Platform: UNKNOWN
